higgs/__init__.py
higgs/constants.py
higgs/data_types.py
higgs/audio_processing/LICENSE
higgs/audio_processing/higgs_audio_tokenizer.py
higgs/audio_processing/semantic_module.py
higgs/audio_processing/descriptaudiocodec/__init__.py
higgs/audio_processing/descriptaudiocodec/dac/model/base.py
higgs/audio_processing/descriptaudiocodec/dac/model/dac.py
higgs/audio_processing/descriptaudiocodec/dac/nn/layers.py
higgs/audio_processing/descriptaudiocodec/dac/nn/quantize.py
higgs/audio_processing/quantization/__init__.py
higgs/audio_processing/quantization/ac.py
higgs/audio_processing/quantization/core_vq.py
higgs/audio_processing/quantization/core_vq_lsx_version.py
higgs/audio_processing/quantization/ddp_utils.py
higgs/audio_processing/quantization/distrib.py
higgs/audio_processing/quantization/vq.py
higgs/audiotools/__init__.py
higgs/audiotools/post.py
higgs/audiotools/preference.py
higgs/audiotools/core/__init__.py
higgs/audiotools/core/audio_signal.py
higgs/audiotools/core/display.py
higgs/audiotools/core/dsp.py
higgs/audiotools/core/effects.py
higgs/audiotools/core/ffmpeg.py
higgs/audiotools/core/loudness.py
higgs/audiotools/core/playback.py
higgs/audiotools/core/util.py
higgs/audiotools/core/whisper.py
higgs/audiotools/core/templates/__init__.py
higgs/audiotools/core/templates/headers.html
higgs/audiotools/core/templates/pandoc.css
higgs/audiotools/core/templates/widget.html
higgs/audiotools/data/__init__.py
higgs/audiotools/data/datasets.py
higgs/audiotools/data/preprocess.py
higgs/audiotools/data/transforms.py
higgs/audiotools/metrics/__init__.py
higgs/audiotools/metrics/distance.py
higgs/audiotools/metrics/quality.py
higgs/audiotools/metrics/spectral.py
higgs/audiotools/ml/__init__.py
higgs/audiotools/ml/accelerator.py
higgs/audiotools/ml/decorators.py
higgs/audiotools/ml/experiment.py
higgs/audiotools/ml/layers/__init__.py
higgs/audiotools/ml/layers/base.py
higgs/audiotools/ml/layers/spectral_gate.py
higgs/dac/__init__.py
higgs/dac/__main__.py
higgs-0.0.6.dist-info/LICENSE
higgs-0.0.6.dist-info/WHEEL
higgs-0.0.6.dist-info/METADATA
higgs-0.0.6.dist-info/RECORD
