Metadata-Version: 2.1
Name: higgs
Version: 0.0.6
Summary: audio kit
Author-email: calcuis <info@calcu.io>
Classifier: License :: OSI Approved :: MIT License
Requires-Dist: transformers==4.46.3
Project-URL: GitHub, https://github.com/calcuis/text-to-speech-synthesis-3
